tapystry/__init__.py
tapystry/concurrency.py
tapystry/effects.py
tapystry/main.py
tapystry/utils.py
tapystry-0.4.0.dist-info/LICENSE
tapystry-0.4.0.dist-info/METADATA
tapystry-0.4.0.dist-info/WHEEL
tapystry-0.4.0.dist-info/top_level.txt
tapystry-0.4.0.dist-info/RECORD
